Metadata-Version: 2.1
Name: 4to5
Version: 0.0.1
Summary: Replace the number 4 with the number 5.
Home-page: UNKNOWN
Author: Bar Harel
License: UNKNOWN
Platform: UNKNOWN
License-File: LICENSE
